clustermatic/__init__.py
clustermatic/auto_clusterizer.py
clustermatic/bayes_search.py
clustermatic/evaluation.py
clustermatic/model_saver.py
clustermatic/optimization.py
clustermatic/preprocessing.py
clustermatic/random_search.py
clustermatic/scoring.py
clustermatic/utils.py
clustermatic/auxiliary/clustermatic.png
clustermatic/auxiliary/header.png
clustermatic/auxiliary/report_template.html
clustermatic-0.0.3.dist-info/METADATA
clustermatic-0.0.3.dist-info/WHEEL
clustermatic-0.0.3.dist-info/top_level.txt
clustermatic-0.0.3.dist-info/RECORD
