Metadata-Version: 2.1
Name: clustermatic
Version: 0.0.3
Summary: Python AutoML library for clustering tasks
Home-page: https://github.com/AKapich/clustermatic
Author: Aleks Kapich
Author-email: aleks.kapich@gmail.com
Classifier: Programming Language :: Python :: 3
Classifier: License :: OSI Approved :: MIT License
Classifier: Operating System :: OS Independent
Requires-Python: >=3.6
Requires-Dist: scikit-learn~=1.6.0
Requires-Dist: numpy~=1.26.4
Requires-Dist: pandas~=2.0.0
Requires-Dist: scikit-optimize~=0.10.2
Requires-Dist: matplotlib~=3.10.0
Requires-Dist: seaborn~=0.13.2
Requires-Dist: jinja2~=3.1.5
Requires-Dist: pyamg~=5.2.1
